daemonpy/__init__.py
daemonpy/daemon_usage.py
daemonpy/file_descriptor.py
daemonpy/file_process_id.py
daemonpy/py.typed
daemonpy/unix_operations.py
daemonpy-2.0.7.dist-info/licenses/LICENSE
daemonpy-2.0.7.dist-info/METADATA
daemonpy-2.0.7.dist-info/WHEEL
daemonpy-2.0.7.dist-info/top_level.txt
daemonpy-2.0.7.dist-info/RECORD
